{
  "nodes": [
    {
      "id": 2032,
      "name": "XCamp",
      "shape": "circle",
      "image": "https://xcamp.co/netvis/xcamp.png",
      "description": "Auf dem XCamp treffen die Innovationstreiber aus Unternehmen und Start-ups, Design Thinker, Agile und Lean Startup-Experten der Metropolregion Frankfurt Rhein Main zusammen.",
      "url": "https://xcamp.co/",
      "twitterName": "xcamp",
      "open": true,
      "visible": true,
      "keepOpen": true,
      "x": 711.5054730482202,
      "y": 354.34058569131184,
      "links": [
        {"type": "topics", "nodes": [2033, 2034, 2035, 2036]}
      ]
    },
    {
      "id": 2033,
      "name": "Lean Startup",
      "deletable": true,
      "fontSize": 1.2,
      "distance": 50,
      "x": 910.2142051119324,
      "y": 347.95027969706797,
      "links": [
        {"type": "interestedParties", "nodes": [2037, 2038]}
      ]
    },
    {
      "id": 2034,
      "name": "Design Thinking",
      "deletable": true,
      "fontSize": 1.6,
      "distance": 50,
      "x": 569.4120306349729,
      "y": 402.1416625237625,
      "links": [
        {"type": "interestedParties", "nodes": [2038, 2248, 2256]}
      ]
    },
    {
      "id": 2035,
      "name": "Agile",
      "deletable": true,
      "fontSize": 1.4,
      "distance": 50,
      "x": 700.4559721779608,
      "y": 204.76863504174298,
      "links": [
        {"type": "interestedParties", "nodes": [2037, 2038]}
      ]
    },
    {
      "id": 2036,
      "name": "User Experience",
      "deletable": true,
      "fontSize": 1.8,
      "distance": 50,
      "x": 710.1145906384617,
      "y": 504.28222407864234,
      "links": [
        {"type": "interestedParties", "nodes": [2248, 2550]}
      ]
    },
    {
      "id": 2037,
      "name": "Joachim Schirrmacher",
      "shape": "circle",
      "image": "https://www.xing.com/image/0_4_3_72e679b3d_3230655_6/joachim-schirrmacher-foto.256x256.jpg",
      "description": "Software-Developer, Agile, REST, APIs, Lean Camp Organizer, XCamp Organizer, Lean Startup Circle",
      "url": "https://www.linkedin.com/in/joachimschirrmacher/",
      "twitterName": "jschirrmacher",
      "visible": true,
      "connectable": true,
      "x": 850.3376934981387,
      "y": 210.4628366060079,
      "links": [
        {"type": "topics", "nodes": [2033, 2035, 2245, 2275, 2308]}
      ]
    },
    {
      "id": 2038,
      "name": "Christiane Gerigk",
      "shape": "circle",
      "image": "https://www.xing.com/image/1_9_3_3542476e8_3288678_3/christiane-gerigk-foto.256x256.jpg",
      "description": "Dr. Christiane Gerigk arbeitet als Coach und Workshop-Moderatorin mit Teams gezielt in der Frühphase von Innovationsprozessen. Sie vermittelt on-the-Job die geeigneten Methoden aus agiler Entwicklung, Lean-Startup und Design Thinking. Gleichzeitig unterstützt sie Unternehmensleitung und Team dabei, wirkungsvolle organisatorische Voraussetzungen für Agilität in der Organisation zu schaffen.",
      "url": "https://digital-wachsen.de",
      "twitterName": "justsoandme",
      "visible": true,
      "x": 859.2942928984602,
      "y": 489.00505997097554,
      "links": [
        {"type": "topics", "nodes": [2033, 2034, 2035]}
      ]
    },
    {
      "id": 2245,
      "name": "Scrum",
      "deletable": true,
      "distance": 50,
      "links": [
        {"type": "interestedParties", "nodes": [2037]}
      ]
    },
    {
      "id": 2248,
      "name": "Wolf N\u00f6ding",
      "shape": "circle",
      "image": "https://xcamp.co/netvis/persons/0x7563/picture/Wolf_03.png",
      "description": "Als Customer Experience Consultant unterstütze ich Unternehmen in Digitalen Transformations-Projekten. Dabei speziell: Customer Jounrney Entwicklung, Konzepte für neue Online-Services, Omni Channel Modellierung, Prototyping, User Testings.",
      "url": "http://wolfnoeding.de/",
      "visible": true,
      "x": 567.9789545290774,
      "y": 552.1289607777112,
      "links": [
        {"type": "topics", "nodes": [2034, 2036, 2547, 2548, 2549]}
      ]
    },
    {
      "id": 2256,
      "name": "Jens Bothmer",
      "shape": "circle",
      "image": "https://xcamp.co/netvis/persons/0x7555/picture/Jens_Bothmer_683_683_Portraits_Quadrat.png",
      "description": "Mit agilen Innovationsmethoden wie Design Thinking hilft Jens Bothmer Unternehmen dabei, gute Ideen in erfolgreiche Geschäftsmodelle umzusetzen. Aufgrund seines Backgrounds besitzt Jens sehr gutes Fachwissen über Kreativitäts- und Innovationsprozesse von der Ideenentwicklung, über Konzeption bis hin zum Anforderungsmanagement und der Geschäftsmodellierung.\nMehr unter https://goo.gl/fgYNXW",
      "url": "https://www.autentity.de",
      "visible": true,
      "x": 420.20151195628046,
      "y": 417.4060314804536,
      "links": [
        {"type": "topics", "nodes": [2034, 2281, 2282, 2283, 2284]}
      ]
    },
    {
      "id": 2275,
      "name": "Product Management",
      "deletable": true,
      "distance": 50,
      "links": [
        {"type": "interestedParties", "nodes": [2037]}
      ]
    },
    {
      "id": 2281,
      "name": "Transformation",
      "deletable": true,
      "distance": 50,
      "links": [
        {"type": "interestedParties", "nodes": [2256]}
      ]
    },
    {
      "id": 2282,
      "name": "Ideenentwicklung",
      "deletable": true,
      "distance": 50,
      "links": [
        {"type": "interestedParties", "nodes": [2256]}
      ]
    },
    {
      "id": 2283,
      "name": "Confluence",
      "deletable": true,
      "distance": 50,
      "links": [
        {"type": "interestedParties", "nodes": [2256]}
      ]
    },
    {
      "id": 2284,
      "name": "Business Modelling",
      "deletable": true,
      "distance": 50,
      "links": [
        {"type": "interestedParties", "nodes": [2256]}
      ]
    },
    {
      "id": 2299,
      "name": "Team development",
      "deletable": true,
      "distance": 50,
      "links": [
        {"type": "interestedParties", "nodes": [2313]}
      ]
    },
    {
      "id": 2308,
      "name": "Kanban",
      "deletable": true,
      "distance": 50,
      "links": [
        {"type": "interestedParties", "nodes": [2037]}
      ]
    },
    {
      "id": 2313,
      "name": "Bianca  K\u00f6llner",
      "shape": "circle",
      "image": "https://www.xing.com/img/users/f/1/6/71bdbf591.23456580,3.256x256.jpg",
      "description": "Kooperationskultur für digitale Transformation gestalten\nSinnstiftende Formen der Zusammenarbeit für Social Innovation",
      "url": "https://www.xing.com/profile/BiancaNadine_Koellner/cv",
      "visible": true,
      "x": 537.6361392593635,
      "y": 255.52840606216526,
      "links": [
        {"type": "topics", "nodes": [2034, 2035, 2299]}
      ]
    },
    {
      "id": 2547,
      "name": "Customer Experience",
      "deletable": true,
      "distance": 50,
      "links": [
        {"type": "interestedParties", "nodes": [2248]}
      ]
    },
    {
      "id": 2548,
      "name": "Lean UX",
      "deletable": true,
      "distance": 50,
      "links": [
        {"type": "interestedParties", "nodes": [2248]}
      ]
    },
    {
      "id": 2549,
      "name": "UX in Agile",
      "deletable": true,
      "distance": 50,
      "links": [
        {"type": "interestedParties", "nodes": [2248]}
      ]
    },
    {
      "id": 2550,
      "name": "Stefan Trost",
      "shape": "circle",
      "image": "https://xcamp.co/netvis/persons/0x755c/picture/4-small.JPG",
      "description": "Ich bin Web Entwickler mit großem Interesse an Produktentwicklung.",
      "url": "https://www.stefantrost.co",
      "visible": true,
      "x": 741.8714797573193,
      "y": 650.8794060915146,
      "links": [
        {"type": "topics", "nodes": [2036]}
      ]
    }
  ]
}
